chaptinator/__init__.py
chaptinator/__main__.py
chaptinator/chaptinator.py
chaptinator-0.6.dist-info/LICENSE
chaptinator-0.6.dist-info/METADATA
chaptinator-0.6.dist-info/WHEEL
chaptinator-0.6.dist-info/entry_points.txt
chaptinator-0.6.dist-info/top_level.txt
chaptinator-0.6.dist-info/RECORD
