Metadata-Version: 2.1
Name: chaptinator
Version: 0.6
Summary: Add chapters to video based on scene cuts
Home-page: https://github.com/ekut-es/chaptinator
Author: Michael Kuhn & Alexander von Bernuth
Author-email: michael.kuhn@uni-tuebingen.de
License: Unlicense
Platform: UNKNOWN
Classifier: Programming Language :: Python :: 3.8
Classifier: Operating System :: OS Independent
Requires-Python: >=3.8
